src/top.sv
module top (
    input wire [3:0] bcd,
    output logic [6:0] seg7
);

always_comb begin
    case (bcd)
        4'd0: seg7 = 7'b1111110;
        4'd1: seg7 = 7'b0110000;
        4'd2: seg7 = 7'b1101101;
        4'd3: seg7 = 7'b1111001;
        4'd4: seg7 = 7'b0110011;
        4'd5: seg7 = 7'b1011011;
        4'd6: seg7 = 7'b1011111;
        4'd7: seg7 = 7'b1110000;
        4'd8: seg7 = 7'b1111111;
        4'd9: seg7 = 7'b1111011;
        4'd10: seg7 = 7'b1110111;
        4'd11: seg7 = 7'b0011111;
        4'd12: seg7 = 7'b1001110;
        4'd13: seg7 = 7'b0111101;
        4'd14: seg7 = 7'b1001111;
        4'd15: seg7 = 7'b1000111;
        default: seg7 = 7'b0000000;
    endcase
end

endmodule

tb/top_tb.sv
`include "src/top.sv"

module top_tb;
logic [3:0] bcd;
logic [6:0] seg7;

top uut 
(
    .bcd(bcd),
    .seg7(seg7)
);

initial begin
    $dumpfile("build/top.vcd");
    $dumpvars(0, top_tb);
end

initial begin
    for (int i = 0; i < 16; i++) begin
        bcd = i;
        #10;
    end
    #10;
    $finish;
end

endmodule

build/top.vcd
$date
	Tue Apr  7 19:24:27 2026
$end
$version
	Icarus Verilog
$end
$timescale
	1s
$end
$scope module top_tb $end
$var wire 7 ! seg7 [6:0] $end
$var reg 4 " bcd [3:0] $end
$scope module uut $end
$var wire 4 # bcd [3:0] $end
$var reg 7 $ seg7 [6:0] $end
$upscope $end
$scope begin $ivl_for_loop0 $end
$var integer 32 % i [31:0] $end
$upscope $end
$upscope $end
$enddefinitions $end
$comment Show the parameter values. $end
$dumpall
$end
#0
$dumpvars
b0 %
b1111110 $
b0 #
b0 "
b1111110 !
$end
#10
b110000 !
b110000 $
b1 "
b1 #
b1 %
#20
b1101101 !
b1101101 $
b10 "
b10 #
b10 %
#30
b1111001 !
b1111001 $
b11 "
b11 #
b11 %
#40
b110011 !
b110011 $
b100 "
b100 #
b100 %
#50
b1011011 !
b1011011 $
b101 "
b101 #
b101 %
#60
b1011111 !
b1011111 $
b110 "
b110 #
b110 %
#70
b1110000 !
b1110000 $
b111 "
b111 #
b111 %
#80
b1111111 !
b1111111 $
b1000 "
b1000 #
b1000 %
#90
b1111011 !
b1111011 $
b1001 "
b1001 #
b1001 %
#100
b1110111 !
b1110111 $
b1010 "
b1010 #
b1010 %
#110
b11111 !
b11111 $
b1011 "
b1011 #
b1011 %
#120
b1001110 !
b1001110 $
b1100 "
b1100 #
b1100 %
#130
b111101 !
b111101 $
b1101 "
b1101 #
b1101 %
#140
b1001111 !
b1001111 $
b1110 "
b1110 #
b1110 %
#150
b1000111 !
b1000111 $
b1111 "
b1111 #
b1111 %
#160
b10000 %
